[
  {"id":7,"title":"悪食","titleKr":"악식","artist":"pompadolls","tag":"신규","lyrics":[
    {"jp":"「黙ってないで なんか言えお前も」","pron":"다맛테나이데 난까 이에 오마에모","ko":"입 다물고 있지 말고 너도 뭔가 말 좀 해"},
    {"jp":"そう言ったって 言うことなんてない","pron":"소오 잇땃테 이우코토난테나이","ko":"그렇게 말해봤자 말할 거 따윈 없어"},
    {"jp":"なにをして 誰かといても","pron":"나니오시테 다레카토이테모","ko":"뭔가를 하던 누구랑 있던"},
    {"jp":"寂しいばかり ため息ばかり","pron":"사미시이바카리 타메이키바카리","ko":"외롭기만 하고 한숨만 나올 뿐이야"},
    {"jp":"「あいつなんか かまどの火で 焼かれて当然さ」","pron":"아이츠난카 카마도노히데 야까레테 토-젠-사","ko":"저 녀석은 화덕 불로 태워져도 당연해"},
    {"jp":"お前は誰 何様なんだ","pron":"오마에와다레 나니사마난다","ko":"넌 누구야 정체가 뭐야!"},
    {"jp":"どうしようもないな","pron":"도우시요-모 나이나","ko":"어떻게 할 수 있는게 없네"},
    {"jp":"「ねえヘンゼル 置いてきたパン屑を","pron":"네에헨젤, 오이테키타팡쿠즈오","ko":"저기 헨젤, 두고 온 빵 부스러기를"},
    {"jp":"お月様が照らしてくれない」","pron":"오츠키사마가 테라시테쿠레나이","ko":"달님이 비춰주지 않아"},
    {"jp":"「ねえなんで こんなことになったの?」","pron":"네에 난데, 콘나코토니 낫-타노","ko":"저기 어째서, 이렇게 되어 버린 거야?"},
    {"jp":"「大人たちが 食べちゃってたみたいだ」","pron":"오토나타치가 타베챳테타미타이다","ko":"어른들이 먹어버린 모양이야"},
    {"jp":"お食べなさい 遠慮なんかいらないと","pron":"오타베나사이 엔료난카이라나이토","ko":"어서 먹어, 사양은 필요없다고"},
    {"jp":"言われ慣れた 純粋な悪が","pron":"이와레나레타 쥰스이나 아쿠가","ko":"귀에 익숙해진 순수한 악이"},
    {"jp":"お菓子の家を お菓子の家を 食い尽くしたらしいよ","pron":"오카시노이에오 오카시노이에오 쿠이츠쿠시타라시이요","ko":"과자 집을 과자 집을 먹어치운 모양이야"},
    {"jp":"「黙っていたって なんも変わりゃしないさ」","pron":"다맛테이탓테 난모카와랴시나이사","ko":"다물고 있어봤자 아무것도 바뀌지 않아"},
    {"jp":"わかっちゃいるが 舌も気が利かない","pron":"와캇챠이루가 시타모 키가 키카나이","ko":"그런 거 알고는 있지만 혀도 눈치가 없어"},
    {"jp":"何をして 誰かをみても","pron":"나니오시테 다레카오미테모","ko":"무언가를 하고 누군가를 본다고 해도"},
    {"jp":"腐っていつか死んでしまうのに","pron":"쿠삿테 이츠카 신데시마우노니","ko":"썩어서 언젠가 죽어버릴 텐데"},
    {"jp":"「お前なんか あの魔女に食べられて おしまいさ」","pron":"오마에난카 아노마죠오니 타베라레테 오시마이사","ko":"너 따위는 저 마녀한테 먹혀버리고 끝이야"},
    {"jp":"お前は誰 なにがわかるんだ","pron":"오마에와 다레! 나니가 와카룬다","ko":"넌 누구야! 네가 뭘 알아!"},
    {"jp":"放っておいてくれよ","pron":"홋-테 오이테쿠레요","ko":"날 좀 가만히 냅둬"},
    {"jp":"「ねえヘンゼル もし僕が捕まって そしたらひとりで お逃げなさい」","pron":"네에 헨젤, 모시 보쿠가 츠카맛테 소시타라 히토리데 오니게나사이","ko":"저기 헨젤, 만약 내가 붙잡히게 되면 넌 혼자서라도 도망쳐"},
    {"jp":"「ねえなんで みんな眠ってるみたいね","pron":"네에 난데 민-나 네뭇테루미타이네","ko":"어째서, 모두 잠들어 버린 거 같아"},
    {"jp":"食べ疲れて 夢の夜半にいるの?」","pron":"타베츠카레테 유메노 요하니이루노","ko":"먹는 게 지쳐서 꿈나라에 가 있는거야?"},
    {"jp":"お食べなさい 遠慮なんかいらないと","pron":"오타베나사이 엔료난카이라나이토","ko":"어서 먹어, 사양 따위는 필요 없다는"},
    {"jp":"無責任な 純粋な悪は","pron":"무세키닌나 쥰스이나 아쿠와","ko":"무책임한 순수한 악은"},
    {"jp":"おかしなことさえ おかしなことだと気づきやしないよ","pron":"오카시나코토사에 오카시나코토다토 키즈키야시나이요","ko":"이상한 것조차 이상한 것이라고 눈치 채지 못해"},
    {"jp":"なにも なにも 求めまいと","pron":"나니모 나니모 모토메마이토","ko":"그 어떤 것도 원하지 않으려고"},
    {"jp":"誰も 誰も くだらないと","pron":"다레모 다레모 쿠다라나이토","ko":"그 누구도 시시하다고"},
    {"jp":"何を信じて 誰を信じて","pron":"나니오 신지테 다레오 신지테","ko":"무엇을 믿던 누구를 믿던"},
    {"jp":"それでも 話をしようよ","pron":"소레데모 하나시오시요우요","ko":"그럼에도 이야기를 하자"},
    {"jp":"「ねえヘンゼル 置いてきたパン屑が例えば 君の手を取って引いて 」","pron":"네에 헨젤, 오이테키타 팡쿠즈가 타토에바 키미노 테오 톳테 히이테","ko":"저기 헨젤, 두고 온 빵 부스러기가 예를 들어 너의 손을 잡아 당겨서"},
    {"jp":"「ねえなんで あなたがいないみたいね」","pron":"네에 난데 아나타가 이나이미타이네","ko":"어째서, 네가 없는 모양이네"},
    {"jp":"「大人たちが 食べちゃってたみたいだ」","pron":"오토나타치가 타베챳테타 미타이다","ko":"어른들이 다 먹어버린 모양이야"},
    {"jp":"お食べなさい 遠慮なんかいらないと","pron":"오타베나사이 엔료난카이라나이토","ko":"어서 먹어 사양은 필요 없다는"},
    {"jp":"言われ慣れた 純粋な悪が","pron":"이와레나레타 쥰스이나 아쿠가","ko":"많이 들어본 귀에 익숙해진 순수한 악이"},
    {"jp":"お菓子の家を お菓子の家を食い尽くしたらしいよ","pron":"오카시노이에오 오카시노이에오 쿠이츠쿠시타라시이요","ko":"과자 집을 과자 집을 먹어 치워버렸나봐"}
  ]}
]
